NASGrpcFileSystem/__init__.py
NASGrpcFileSystem/code_dict.py
NASGrpcFileSystem/grpc_copy_move_file.py
NASGrpcFileSystem/grpc_create_file.py
NASGrpcFileSystem/grpc_describe_file.py
NASGrpcFileSystem/grpc_file_handle.py
NASGrpcFileSystem/grpc_modify_file.py
NASGrpcFileSystem/grpc_options.py
NASGrpcFileSystem/proto/__init__.py
NASGrpcFileSystem/proto/files_pb2.py
NASGrpcFileSystem/proto/files_pb2_grpc.py
NASGrpcFileSystem2-1.3.8.dist-info/METADATA
NASGrpcFileSystem2-1.3.8.dist-info/WHEEL
NASGrpcFileSystem2-1.3.8.dist-info/top_level.txt
NASGrpcFileSystem2-1.3.8.dist-info/RECORD
