Metadata-Version: 2.1
Name: NASGrpcFileSystem2
Version: 1.3.8
Summary: A python file handler use Grpc client. It used to handle ctec file work, and include: upload and download file from remote, modify file name, copy and move file.
Author: Kepner Wu
Author-email: kepner_wu@hotmail.com
License: MIT
Keywords: CTEC NAS file Grpc system includes create file,get file describe,modify,copy and move file
Platform: all
Classifier: Development Status :: 4 - Beta
Classifier: Intended Audience :: Developers
Classifier: Topic :: Software Development :: Libraries
Classifier: License :: OSI Approved :: MIT License
Classifier: Programming Language :: Python :: 2.7
Classifier: Programming Language :: Python :: 3.5
Classifier: Programming Language :: Python :: 3.6
Classifier: Programming Language :: Python :: 3.7
Classifier: Programming Language :: Python :: 3.10
Requires-Dist: future ==0.18.2
Requires-Dist: grpcio >=1.30.0
Requires-Dist: werkzeug ==0.15.4
Requires-Dist: protobuf ==3.12.2
